{
  "todos": [
    {
      "id": 1,
      "name": "Học React"
    },
    {
      "id": 2,
      "name": "Học NextJS"
    },
    {
      "id": 3,
      "name": "Học NodeJS"
    },
    {
      "id": 4,
      "name": "Học Javascript"
    },
    {
      "id": 5,
      "name": "Học HTML"
    },
    {
      "name": "Học Java",
      "id": 6
    },
    {
      "name": "Học C#",
      "id": 7
    },
    {
      "name": "Học nấu ăn",
      "id": 8
    },
    {
      "name": "Dạy Fullstack Offline",
      "id": 9
    },
    {
      "name": "Ngủ",
      "id": 10
    },
    {
      "name": "ABC",
      "id": 11
    },
    {
      "name": "Hello",
      "id": 12
    },
    {
      "name": "csavd",
      "id": 13
    },
    {
      "name": "Vũ Đức Tài",
      "id": 14
    },
    {
      "name": "vsdcd",
      "id": 15
    },
    {
      "name": "vdf",
      "id": 16
    },
    {
      "name": "Hoàng An",
      "id": 17
    },
    {
      "name": "csc",
      "id": 18
    },
    {
      "name": "gdf",
      "id": 19
    }
  ],
  "posts": [
    {
      "title": "Bùi Quang Trưởng",
      "id": 1
    },
    {
      "title": "Kiều Duy Tùng",
      "id": 2
    },
    {
      "title": "Lưu Anh Quân",
      "id": 3
    },
    {
      "title": "Tạ Hoàng An",
      "id": 4
    },
    {
      "title": "ABC",
      "id": 5
    },
    {
      "title": "Nguyễn Dương",
      "id": 6
    },
    {
      "title": "ABC",
      "id": 7
    }
  ]
}